pytest_rail/__init__.py
pytest_rail/conftest.py
pytest_rail/plugin.py
pytest_rail/testrail_api.py
pytest_rail-1.0.5.dist-info/LICENSE
pytest_rail-1.0.5.dist-info/METADATA
pytest_rail-1.0.5.dist-info/WHEEL
pytest_rail-1.0.5.dist-info/entry_points.txt
pytest_rail-1.0.5.dist-info/top_level.txt
pytest_rail-1.0.5.dist-info/RECORD
