Metadata-Version: 2.1
Name: pytest-rail
Version: 1.0.5
Summary: pytest plugin for creating TestRail runs and adding results
Home-page: http://github.com/anukchat/pytest-rail/
Author: Anukool Chaturvedi
Author-email: chaturvedianukool@gmail.com
License: UNKNOWN
Platform: UNKNOWN
License-File: LICENSE
Requires-Dist: pytest (>=3.6)
Requires-Dist: requests (>=2.20.0)
